{
   "jazyk": "german",
   "datum": "2021-10-07 16:25:05.566048",
   "podle": "kategorie",
   "podle_meta": "zv\u00ed\u0159e",
   "seznam_id_slovicek": [
      8,
      9,
      84,
      78,
      87,
      2,
      10,
      7,
      83,
      76,
      88,
      0,
      93,
      94,
      89
   ],
   "seznam_odpovedi": [
      "skipped",
      "skipped",
      "skipped",
      "skipped",
      "skipped",
      "skipped",
      "skipped",
      "skipped",
      "skipped",
      "skipped",
      "skipped",
      "skipped",
      "skipped",
      "skipped",
      "skipped"
   ],
   "poznamka": "None, p\u0159ezkou\u0161en\u00ed z 2021-10-07 01:02:09.468813"
}